LICENSE
README.md
pyproject.toml
setup.py
python_rmap.egg-info/PKG-INFO
python_rmap.egg-info/SOURCES.txt
python_rmap.egg-info/dependency_links.txt
python_rmap.egg-info/entry_points.txt
python_rmap.egg-info/top_level.txt
rmap/__init__.py
rmap/banner.py
rmap/main.py
rmap/nmap.py
rmap/scan.py
rmap/utils.py