Metadata-Version: 2.1
Name: python-rmap
Version: 0.2.5
Summary: Automated enumeration for red teamers
Home-page: https://github.com/syspuke/rmap
Author: syspuke
Author-email: syspuke@pm.me
License: gpl-3.0
Requires-Python: >=3.6
License-File: LICENSE
